Workbook

Sheet Итог
A1: Камчатскэнерго 32616346943 — арматура среднего и низкого давления (Лот 0200-РЕМ ПРОД-2027-КамчЭн)
A2: Конкурс в эл. форме, 223-ФЗ, Росэлторг (секция РусГидро). Подача до 29.10.2026. НМЦК с НДС. Наша цена = цена договора (УСН).
A3: Показатель | B3: Значение | C3: Комментарий
A4: НМЦК, ₽ | B4: 101102908 | C4: весь лот, 315 позиций, 3 383 ед., 4 грузополучателя
A5: Позиций с ценой | B5: =COUNT(Позиции!J3:J317) | C5: из 315; пустые — ищем, можно вписать вручную на листе «Позиции»
A6: Себестоимость по найденным позициям (после торга −10%, с доставкой), ₽ | B6: =Позиции!O318 | C6: сумма столбца O листа «Позиции»
A7: Оценка себестоимости всего лота, ₽ | B7: =IF(COUNT(Позиции!J3:J317)=0,65661745.0,B6/MAX(B5,1)*315) | C7: пока цен нет — оценка по истории лотов (60% НМЦК + 5 млн доставка); по мере заполнения — экстраполяция по найденным
A8: Маржа при НМЦК | B8: =1-B7/B4
A9: Ожидаемое снижение на конкурсе | B9: 0.15 | C9: история: −7% … −23% (2025–2026), большинство заявок отклоняют
A10: Цена заявки, ₽ | B10: =B4*(1-B9)
A11: Прибыль до налога, ₽ | B11: =B10-B7-0.008*B10-B7*0.2*120/365 | C11: 0,8% ЭП/банк, деньги 20% годовых на 120 дней
A12: Прибыль после УСН 15%, ₽ | B12: =B11-0.15*MAX(B11,0)
A13: Маржа к цене заявки | B13: =B12/B10
A15: Сценарии снижения | B15: Прибыль после УСН, ₽
A16: −0% | B16: =(B4*(1-0)-B7-0.008*B4*(1-0)-B7*0.2*120/365)*IF(B4*(1-0)-B7-0.008*B4*(1-0)-B7*0.2*120/365>0,0.85,1)
A17: −7% | B17: =(B4*(1-0.07)-B7-0.008*B4*(1-0.07)-B7*0.2*120/365)*IF(B4*(1-0.07)-B7-0.008*B4*(1-0.07)-B7*0.2*120/365>0,0.85,1)
A18: −15% | B18: =(B4*(1-0.15)-B7-0.008*B4*(1-0.15)-B7*0.2*120/365)*IF(B4*(1-0.15)-B7-0.008*B4*(1-0.15)-B7*0.2*120/365>0,0.85,1)
A19: −23% | B19: =(B4*(1-0.23)-B7-0.008*B4*(1-0.23)-B7*0.2*120/365)*IF(B4*(1-0.23)-B7-0.008*B4*(1-0.23)-B7*0.2*120/365>0,0.85,1)
A20: −30% | B20: =(B4*(1-0.3)-B7-0.008*B4*(1-0.3)-B7*0.2*120/365)*IF(B4*(1-0.3)-B7-0.008*B4*(1-0.3)-B7*0.2*120/365>0,0.85,1)
A22: Условия
A23: Поставка | B23: в течение 120 календарных дней с подписания договора; Петропавловск-Камчатский (ул. Пограничная 75А, ул. Степная 50, пр. Победы 24) и Елизовский р-н, пос. Светлый
A24: Обеспечение заявки | B24: 1 005 499,42 ₽ (БГ или деньги)
A25: Аванс | B25: предусмотрен; обеспечение возврата аванса — 100% суммы аванса (БГ); размер — в проекте договора
A26: Гарантия | B26: по заводу, не менее 12 мес.; изготовление — год поставки или предыдущий
A27: Нацрежим | B27: ПП 1875 — ограничение + преимущество: по каждой позиции номер записи в реестре Минпромторга/ЕАЭС
A28: Документы | B28: сертификаты/декларации ТР ТС 032/2013 и 010/2011 со схемами 1с/5Д и протоколами испытаний; техпредложение по Прил. 1
A29: Аккредитация | B29: аккредитация в РусГидро (Прил. 10)
A30: Подача на часть лота | B30: нельзя — лот неделимый
A31: Эквиваленты | B31: допускаются, марка носит описательный характер; нужно обоснование эквивалентности
A33: История лотов Камчатскэнерго
A34: 13000-РЕМ ПРОД-2026-КамчЭн | B34: НМЦК 119 527 144 ₽ → победитель 92043800; снижение 0.23 | C34: 4 из 6 (п.4.9.6 а — состав/оформление заявки), включая 47.8 и 89.999 млн
A35: 25900-РЕМ ПРОД-2025-КамчЭн | B35: НМЦК 85 866 140 ₽ → победитель 79900000; снижение 0.07 | C35: 0 из 3
A36: 1000-РЕМ ПРОД-2026-КамчЭн (арматура среднего давления) | B36: НМЦК 52 886 220 ₽ → победитель 52100110; снижение 0.015 | C36: 9 из 10 — допущена только заявка 52.1 млн
A37: 0100-РЕМ ПРОД-2027-КамчЭн (арматура высокого давления) | B37: НМЦК 180 965 509 ₽ → победитель 157097600; снижение 0.132 | C37: 0 из 2

Sheet Позиции
A1: Камчатскэнерго 32616346943 — позиции, количества, себестоимость (заполненные цены — рынок 2026 с НДС; пустые — ещё ищем, можно вписать вручную)
A2: Таблица | B2: № | C2: Позиция | D2: Кол-во | E2: Ед. | F2: DN | G2: PN, МПа | H2: Материал корпуса | I2: Привод | J2: Цена за ед. (рынок), ₽ | K2: Цена после торга −10%, ₽ | L2: Вес ед., кг | M2: Сумма закупки, ₽ | N2: Доставка, ₽ | O2: Себестоимость позиции, ₽ | P2: Поставщик | Q2: Тип цены / подтверждение 2026 | R2: Аналог / реестр МПТ | S2: Ссылка
A3: 1.1 | B3: 1 | C3: Клапан предохранительный 17лс17нж Ду 200-300 Ру 16-6 полноподъемный пружинный фланцевый | D3: 1 | E3: шт | F3: 200 | G3: 1.6 | H3: Корпус — сталь 20ГЛ ГОСТ 977-88; Крышка | I3: автоматическое/ручное | K3: =IF(J3="","",J3*(1-0.1)) | M3: =IF(J3="","",K3*D3) | N3: =IF(L3="","",L3*D3*55) | O3: =IF(M3="","",M3+N(N3))
A4: 1.1 | B4: 2 | C4: Клапан запорный 15нж65нж Ду 200 Ру 16 | D4: 4 | E4: шт | F4: 200 | G4: 1.6 | H4: 12Х18Н10Т | I4: Ручное | K4: =IF(J4="","",J4*(1-0.1)) | M4: =IF(J4="","",K4*D4) | N4: =IF(L4="","",L4*D4*55) | O4: =IF(M4="","",M4+N(N4))
A5: 1.1 | B5: 3 | C5: Клапан запорный15нж65нж Ду 50 Ру 16 | D5: 3 | E5: шт | F5: 50 | G5: 1.6 | H5: 12Х18Н10Т | I5: Ручное | K5: =IF(J5="","",J5*(1-0.1)) | M5: =IF(J5="","",K5*D5) | N5: =IF(L5="","",L5*D5*55) | O5: =IF(M5="","",M5+N(N5))
A6: 1.1 | B6: 4 | C6: Клапан запорный15с52нж11 Ду 32 Ру 63 под приварку | D6: 12 | E6: шт | F6: 32 | G6: 6.3 | H6: Сталь 20 | I6: ручное | K6: =IF(J6="","",J6*(1-0.1)) | M6: =IF(J6="","",K6*D6) | N6: =IF(L6="","",L6*D6*55) | O6: =IF(M6="","",M6+N(N6))
A7: 1.1 | B7: 5 | C7: Задвижка 30нж41нж Ду 150 Ру 16 1исп. САЗ | D7: 1 | E7: шт | F7: 150 | G7: 1.6 | H7: сталь 12Х18Н9ТЛ | I7: ручной (маховик) | K7: =IF(J7="","",J7*(1-0.1)) | M7: =IF(J7="","",K7*D7) | N7: =IF(L7="","",L7*D7*55) | O7: =IF(M7="","",M7+N(N7))
A8: 1.1 | B8: 6 | C8: Задвижка 30нж947нж Ду 1000 Ру 4 | D8: 1 | E8: шт | F8: 1000 | G8: 0.4 | H8: Ст.12Х18Н10Т | I8: Под привод , тип присоединения | K8: =IF(J8="","",J8*(1-0.1)) | M8: =IF(J8="","",K8*D8) | N8: =IF(L8="","",L8*D8*55) | O8: =IF(M8="","",M8+N(N8))
A9: 1.1 | B9: 7 | C9: Задвижка 30с41нж Ду 50 Ру 16 | D9: 10 | E9: шт | F9: 50 | G9: 1.6 | H9: Сталь 25 Л | I9: Ручное | K9: =IF(J9="","",J9*(1-0.1)) | M9: =IF(J9="","",K9*D9) | N9: =IF(L9="","",L9*D9*55) | O9: =IF(M9="","",M9+N(N9))
A10: 1.1 | B10: 8 | C10: Задвижка 30с41нж Ду 100 Ру 16 | D10: 7 | E10: шт | F10: 100 | G10: 1.6 | H10: сталь 25Л | I10: ручной (маховик) | K10: =IF(J10="","",J10*(1-0.1)) | M10: =IF(J10="","",K10*D10) | N10: =IF(L10="","",L10*D10*55) | O10: =IF(M10="","",M10+N(N10))
A11: 1.1 | B11: 9 | C11: Задвижка 30с41нж Ду 150 Ру 16 | D11: 10 | E11: шт | F11: 150 | G11: 1.6 | H11: сталь 25Л | I11: ручной (маховик) | K11: =IF(J11="","",J11*(1-0.1)) | M11: =IF(J11="","",K11*D11) | N11: =IF(L11="","",L11*D11*55) | O11: =IF(M11="","",M11+N(N11))
A12: 1.1 | B12: 10 | C12: Задвижка клиновая фланцевая 30с41нж Ду 300 Ру 16 с КОФ | D12: 2 | E12: шт | F12: 300 | G12: 1.6 | H12: сталь 25Л | I12: Ручное | K12: =IF(J12="","",J12*(1-0.1)) | M12: =IF(J12="","",K12*D12) | N12: =IF(L12="","",L12*D12*55) | O12: =IF(M12="","",M12+N(N12))
A13: 1.1 | B13: 11 | C13: Задвижка 30С576НЖ Ду 300 Ру 63 с редуктором РК-Г-1М, в комплекте с крепежом и ответными фланцами. | D13: 2 | E13: шт | F13: 300 | G13: 6.3 | H13: Сталь 25Л | I13: редуктор РК-Г1 | K13: =IF(J13="","",J13*(1-0.1)) | M13: =IF(J13="","",K13*D13) | N13: =IF(L13="","",L13*D13*55) | O13: =IF(M13="","",M13+N(N13))
A14: 1.1 | B14: 12 | C14: Задвижка клиновая фланцевая 30с941нж Ду 500 Ру 16 с КОФ под электропривод Bernard ST-30 | D14: 1 | E14: шт | F14: 500 | G14: 1,6 МПа | H14: сталь 25Л | I14: под электропривод | K14: =IF(J14="","",J14*(1-0.1)) | M14: =IF(J14="","",K14*D14) | N14: =IF(L14="","",L14*D14*55) | O14: =IF(M14="","",M14+N(N14))
A15: 1.1 | B15: 13 | C15: Задвижка 30с964нж Ду 300 Ру 25 | D15: 1 | E15: шт | F15: 300 | G15: 2.5 | H15: Сталь 25Л | I15: Под привод, ручное | K15: =IF(J15="","",J15*(1-0.1)) | M15: =IF(J15="","",K15*D15) | N15: =IF(L15="","",L15*D15*55) | O15: =IF(M15="","",M15+N(N15))
A16: 1.1 | B16: 14 | C16: Кран шаровой 11б27п1 Ду 15 Ру 16 | D16: 35 | E16: шт | F16: 15 | G16: 1.6 | H16: латунь HPb58-2A | I16: Ручное | K16: =IF(J16="","",J16*(1-0.1)) | M16: =IF(J16="","",K16*D16) | N16: =IF(L16="","",L16*D16*55) | O16: =IF(M16="","",M16+N(N16))
A17: 1.1 | B17: 15 | C17: Кран шаровой 11б27п1 Ду 20 Ру 16 | D17: 35 | E17: шт | F17: 20 | G17: 1.6 | H17: латунь HPb58-2A | I17: Ручное | K17: =IF(J17="","",J17*(1-0.1)) | M17: =IF(J17="","",K17*D17) | N17: =IF(L17="","",L17*D17*55) | O17: =IF(M17="","",M17+N(N17))
A18: 1.1 | B18: 16 | C18: Кран шаровой 11б27п1 Ду 25 Ру 16 | D18: 20 | E18: шт | F18: 25 | G18: 1.6 | H18: латунь HPb58-2A | I18: Ручное | K18: =IF(J18="","",J18*(1-0.1)) | M18: =IF(J18="","",K18*D18) | N18: =IF(L18="","",L18*D18*55) | O18: =IF(M18="","",M18+N(N18))
A19: 1.1 | B19: 17 | C19: Кран шаровой 11б27п1 Ду 32 Ру 16 | D19: 25 | E19: шт | F19: 32 | G19: 1.6 | H19: латунь HPb58-2A | I19: Ручное | K19: =IF(J19="","",J19*(1-0.1)) | M19: =IF(J19="","",K19*D19) | N19: =IF(L19="","",L19*D19*55) | O19: =IF(M19="","",M19+N(N19))
A20: 1.1 | B20: 18 | C20: Кран шаровой 11б27п1 Ду 40 Ру 16 | D20: 8 | E20: шт | F20: 40 | G20: 1.6 | H20: латунь HPb58-2A | I20: Ручное | K20: =IF(J20="","",J20*(1-0.1)) | M20: =IF(J20="","",K20*D20) | N20: =IF(L20="","",L20*D20*55) | O20: =IF(M20="","",M20+N(N20))
A21: 1.1 | B21: 19 | C21: Кран шаровой 11б27п1 Ду 50 Ру 16 | D21: 8 | E21: шт | F21: 50 | G21: 1.6 | H21: латунь HPb58-2A | I21: Ручное | K21: =IF(J21="","",J21*(1-0.1)) | M21: =IF(J21="","",K21*D21) | N21: =IF(L21="","",L21*D21*55) | O21: =IF(M21="","",M21+N(N21))
A22: 1.1 | B22: 20 | C22: Кран шаровой 11с67п Ду 150 Ру 25 цельносварной под приварку | D22: 2 | E22: шт | F22: 150 | G22: 2.5 | H22: Сталь 20 | I22: Ручное | K22: =IF(J22="","",J22*(1-0.1)) | M22: =IF(J22="","",K22*D22) | N22: =IF(L22="","",L22*D22*55) | O22: =IF(M22="","",M22+N(N22))
A23: 1.1 | B23: 21 | C23: Кран шаровой 11с67п Ду 200 Ру 16 ЦУФ.001 КШ укороченный полнопроходной фланцевый с рукояткой | D23: 2 | E23: шт | F23: 200 | G23: 1.6 | H23: Сталь 20 | I23: Ручное | K23: =IF(J23="","",J23*(1-0.1)) | M23: =IF(J23="","",K23*D23) | N23: =IF(L23="","",L23*D23*55) | O23: =IF(M23="","",M23+N(N23))
A24: 1.1 | B24: 22 | C24: Затвор дисковый поворотный межфланцевый Stensel 31070-01 Ду 200 Ру 25 | D24: 3 | E24: шт | F24: 200 | G24: 2.5 | H24: Корпус - нержавеющая сталь | I24: Верхний фланец выполнен по ста | K24: =IF(J24="","",J24*(1-0.1)) | M24: =IF(J24="","",K24*D24) | N24: =IF(L24="","",L24*D24*55) | O24: =IF(M24="","",M24+N(N24))
A25: 1.1 | B25: 23 | C25: Затвор дисковый поворотный межфланцевый ПА954.450.10-05 Ду 450 Ру 10 | D25: 1 | E25: шт | F25: 450 | G25: 1 | H25: Корпус - коррозионностойкая молибденосод | I25: Редуктор DN 450 | K25: =IF(J25="","",J25*(1-0.1)) | M25: =IF(J25="","",K25*D25) | N25: =IF(L25="","",L25*D25*55) | O25: =IF(M25="","",M25+N(N25))
A26: 1.1 | B26: 24 | C26: Электропривод общепромышленный Н-В-02 У2 | D26: 2 | E26: шт | F26: Под задвижку 30с964нж Ду 300 | G26: - | H26: - | I26: Электропривод Н-В-02 У2 | K26: =IF(J26="","",J26*(1-0.1)) | M26: =IF(J26="","",K26*D26) | N26: =IF(L26="","",L26*D26*55) | O26: =IF(M26="","",M26+N(N26))
A27: 1.2 | B27: 1 | C27: Кран шаровой 11с67п Ду 32 Ру 25 цельносварной под приварку | D27: 2 | E27: шт | F27: 32 | G27: 2.5 | H27: сталь 20 | I27: ручной (рукоятка) | K27: =IF(J27="","",J27*(1-0.1)) | M27: =IF(J27="","",K27*D27) | N27: =IF(L27="","",L27*D27*55) | O27: =IF(M27="","",M27+N(N27))
A28: 1.2 | B28: 2 | C28: Кран шаровой 11с67п Ду 100 Ру 25 цельносварной под приварку | D28: 4 | E28: шт | F28: 100 | G28: 2.5 | H28: сталь 20 | I28: ручное | K28: =IF(J28="","",J28*(1-0.1)) | M28: =IF(J28="","",K28*D28) | N28: =IF(L28="","",L28*D28*55) | O28: =IF(M28="","",M28+N(N28))
A29: 1.2 | B29: 3 | C29: Кран шаровой 11с67п Ду 50 Ру 25 полнопрох. с КОФ (КЗШС41нж) | D29: 18 | E29: шт | F29: 50 | G29: 2.5 | H29: сталь 20 | I29: Ручное | K29: =IF(J29="","",J29*(1-0.1)) | M29: =IF(J29="","",K29*D29) | N29: =IF(L29="","",L29*D29*55) | O29: =IF(M29="","",M29+N(N29))
A30: 1.2 | B30: 4 | C30: Кран шаровой 11с67п Ду 80 Ру 25 полнопрох. с КОФ (КЗШС41нж) | D30: 4 | E30: шт | F30: 80 | G30: 2.5 | H30: сталь 20 | I30: Ручное | K30: =IF(J30="","",J30*(1-0.1)) | M30: =IF(J30="","",K30*D30) | N30: =IF(L30="","",L30*D30*55) | O30: =IF(M30="","",M30+N(N30))
A31: 1.2 | B31: 5 | C31: Кран шаровой 11с67п Ду 100 Ру 16 ЦУФ.001 КШ укороченный полнопроходной фланцевый с рукояткой | D31: 2 | E31: шт | F31: 100 | G31: 1.6 | H31: сталь 20 | I31: ручное | K31: =IF(J31="","",J31*(1-0.1)) | M31: =IF(J31="","",K31*D31) | N31: =IF(L31="","",L31*D31*55) | O31: =IF(M31="","",M31+N(N31))
A32: 1.3 | B32: 1 | C32: Клапан регулирующий 25с947нж Ду 50 Ру 25 с ЭИМ | D32: 1 | E32: шт | F32: 50 | G32: 2.5 | H32: Сталь марки 25Л ГОСТ 977-88 | I32: электропривод | K32: =IF(J32="","",J32*(1-0.1)) | M32: =IF(J32="","",K32*D32) | N32: =IF(L32="","",L32*D32*55) | O32: =IF(M32="","",M32+N(N32))
A33: 1.3 | B33: 2 | C33: Клапан регулирующий 25ч945п Ду 15 Ру 16 с ЭИМ | D33: 2 | E33: шт | F33: 15 | G33: 1.6 | H33: чугун СЧ20 | I33: автоматический | K33: =IF(J33="","",J33*(1-0.1)) | M33: =IF(J33="","",K33*D33) | N33: =IF(L33="","",L33*D33*55) | O33: =IF(M33="","",M33+N(N33))
A34: 1.3 | B34: 3 | C34: Клапан регулирующий 25ч945п Ду 25 Ру 16 с ЭИМ | D34: 1 | E34: шт | F34: 25 | G34: 1.6 | H34: чугун СЧ20 | I34: автоматический | K34: =IF(J34="","",J34*(1-0.1)) | M34: =IF(J34="","",K34*D34) | N34: =IF(L34="","",L34*D34*55) | O34: =IF(M34="","",M34+N(N34))
A35: 1.3 | B35: 4 | C35: Клапан регулирующий 25ч945п Ду 50 Ру 16 KV100 с ЭИМ | D35: 2 | E35: шт | F35: 50 | G35: 1.6 | H35: чугун СЧ20 | I35: автоматический | K35: =IF(J35="","",J35*(1-0.1)) | M35: =IF(J35="","",K35*D35) | N35: =IF(L35="","",L35*D35*55) | O35: =IF(M35="","",M35+N(N35))
A36: 1.3 | B36: 5 | C36: Клапан регулирующий 25ч945п Ду 80 Ру 16 с ЭИМ | D36: 8 | E36: шт | F36: 80 | G36: 1.6 | H36: чугун СЧ20 | I36: автоматический | K36: =IF(J36="","",J36*(1-0.1)) | M36: =IF(J36="","",K36*D36) | N36: =IF(L36="","",L36*D36*55) | O36: =IF(M36="","",M36+N(N36))
A37: 1.3 | B37: 6 | C37: Регулирующий клапан Ридан VFG-2R Ду 100, Kvs 125, Ру 16 | D37: 2 | E37: шт | F37: 100 | G37: 1.6 | H37: Углеродистая сталь WCB | K37: =IF(J37="","",J37*(1-0.1)) | M37: =IF(J37="","",K37*D37) | N37: =IF(L37="","",L37*D37*55) | O37: =IF(M37="","",M37+N(N37))
A38: 1.3 | B38: 7 | C38: Регулирующий клапан Ридан VFG-2R Ду 32, Kvs 16, Ру 16 | D38: 4 | E38: шт | F38: 32 | G38: 1.6 | H38: Углеродистая сталь WCB | K38: =IF(J38="","",J38*(1-0.1)) | M38: =IF(J38="","",K38*D38) | N38: =IF(L38="","",L38*D38*55) | O38: =IF(M38="","",M38+N(N38))
A39: 1.3 | B39: 8 | C39: регулирующий клапан Ридан VFG-2R Ду 80, Kvs 80, Ру 16 | D39: 2 | E39: шт | F39: 80 | G39: 1.6 | H39: Углеродистая сталь WCB | K39: =IF(J39="","",J39*(1-0.1)) | M39: =IF(J39="","",K39*D39) | N39: =IF(L39="","",L39*D39*55) | O39: =IF(M39="","",M39+N(N39))
A40: 1.3 | B40: 9 | C40: Регулятор давления РД-НО (Нормально открытый) Ду 25 Ру 16 | D40: 2 | E40: шт | F40: 25 | G40: 1.6 | H40: чугун СЧ20 ГОСТ1412 | I40: автоматически действующая труб | K40: =IF(J40="","",J40*(1-0.1)) | M40: =IF(J40="","",K40*D40) | N40: =IF(L40="","",L40*D40*55) | O40: =IF(M40="","",M40+N(N40))
A41: 1.3 | B41: 10 | C41: Регулятор давления РД-НО (Нормально открытый) Ду 32 Ру 16 | D41: 1 | E41: шт | F41: 32 | G41: 1.6 | H41: чугун СЧ20 ГОСТ1412 | I41: автоматический | K41: =IF(J41="","",J41*(1-0.1)) | M41: =IF(J41="","",K41*D41) | N41: =IF(L41="","",L41*D41*55) | O41: =IF(M41="","",M41+N(N41))
A42: 1.3 | B42: 11 | C42: Регулятор давления РД-НО (Нормально открытый) Ду 50 Ру 16 | D42: 3 | E42: шт | F42: 50 | G42: 1.6 | H42: чугун СЧ20 ГОСТ1412 | I42: автоматический | K42: =IF(J42="","",J42*(1-0.1)) | M42: =IF(J42="","",K42*D42) | N42: =IF(L42="","",L42*D42*55) | O42: =IF(M42="","",M42+N(N42))
A43: 1.3 | B43: 12 | C43: Регулятор давления РД-НО (Нормально открытый) Ду 80 Ру 16 | D43: 3 | E43: шт | F43: 80 | G43: 1.6 | H43: Сталь марки 20 | I43: автоматический | K43: =IF(J43="","",J43*(1-0.1)) | M43: =IF(J43="","",K43*D43) | N43: =IF(L43="","",L43*D43*55) | O43: =IF(M43="","",M43+N(N43))
A44: 1.3 | B44: 13 | C44: Регулирующий блок после себя AFD Ду 15-250 с диапазоном настройки Ру 25 | D44: 2 | E44: шт | F44: 15-250 | G44: Условное давление датчика (PN), погружная гильза, 2,5 | H44: Нержавеющая сталь | I44: отсутствует | K44: =IF(J44="","",J44*(1-0.1)) | M44: =IF(J44="","",K44*D44) | N44: =IF(L44="","",L44*D44*55) | O44: =IF(M44="","",M44+N(N44))
A45: 1.3 | B45: 14 | C45: Клапан обратный 19с53нж Ду 80 Ру 40 | D45: 2 | E45: шт | F45: 80 | G45: 4 | H45: Углеродистая сталь | K45: =IF(J45="","",J45*(1-0.1)) | M45: =IF(J45="","",K45*D45) | N45: =IF(L45="","",L45*D45*55) | O45: =IF(M45="","",M45+N(N45))
A46: 1.3 | B46: 15 | C46: Клапан обратный 19с53нж Ду 150 Ру 40 | D46: 2 | E46: шт | F46: 150 | G46: 4 | H46: Углеродистая сталь | K46: =IF(J46="","",J46*(1-0.1)) | M46: =IF(J46="","",K46*D46) | N46: =IF(L46="","",L46*D46*55) | O46: =IF(M46="","",M46+N(N46))
A47: 1.3 | B47: 16 | C47: Клапан обратный межфланцевый 19ч21бр Ду 100 Ру 16 | D47: 4 | E47: шт | F47: 100 | G47: 1.6 | H47: чугун СЧ18 | I47: автоматический | K47: =IF(J47="","",J47*(1-0.1)) | M47: =IF(J47="","",K47*D47) | N47: =IF(L47="","",L47*D47*55) | O47: =IF(M47="","",M47+N(N47))
A48: 1.3 | B48: 17 | C48: Клапан обратный межфланцевый 19ч21бр Ду 50 Ру 16 | D48: 6 | E48: шт | F48: 50 | G48: 1.6 | H48: чугун СЧ18 | I48: автоматический | K48: =IF(J48="","",J48*(1-0.1)) | M48: =IF(J48="","",K48*D48) | N48: =IF(L48="","",L48*D48*55) | O48: =IF(M48="","",M48+N(N48))
A49: 1.3 | B49: 18 | C49: Клапан обратный межфланцевый 19ч21бр Ду 80 Ру 16 | D49: 7 | E49: шт | F49: 80 | G49: 1.6 | H49: чугун СЧ18 | I49: автоматический | K49: =IF(J49="","",J49*(1-0.1)) | M49: =IF(J49="","",K49*D49) | N49: =IF(L49="","",L49*D49*55) | O49: =IF(M49="","",M49+N(N49))
A50: 1.3 | B50: 19 | C50: Клапан обратный двухстворчатый DENDOR 010C Ду 100 Ру 16 | D50: 5 | E50: шт | F50: 100 | G50: 1.6 | H50: Чугун EN-GJS-400-15 | I50: - | K50: =IF(J50="","",J50*(1-0.1)) | M50: =IF(J50="","",K50*D50) | N50: =IF(L50="","",L50*D50*55) | O50: =IF(M50="","",M50+N(N50))
A51: 1.3 | B51: 20 | C51: Клапан обратный двухстворчатый DENDOR 010C Ду 200 Ру 16 | D51: 5 | E51: шт | F51: 200 | G51: 1.6 | H51: Чугун EN-GJS-400-15 | I51: - | K51: =IF(J51="","",J51*(1-0.1)) | M51: =IF(J51="","",K51*D51) | N51: =IF(L51="","",L51*D51*55) | O51: =IF(M51="","",M51+N(N51))
A52: 1.3 | B52: 21 | C52: Клапан обратный фланцевый Ду 50 Ру 40 | D52: 1 | E52: шт | F52: 50 | G52: 4 | H52: Углеродистая сталь | K52: =IF(J52="","",J52*(1-0.1)) | M52: =IF(J52="","",K52*D52) | N52: =IF(L52="","",L52*D52*55) | O52: =IF(M52="","",M52+N(N52))
A53: 1.3 | B53: 22 | C53: Обратный клапан «Гранлок» серии CV16 Ду 150 Ру 16 | D53: 4 | E53: шт | F53: 150 | G53: 1.6 | H53: чугун GG25 | I53: - | K53: =IF(J53="","",J53*(1-0.1)) | M53: =IF(J53="","",K53*D53) | N53: =IF(L53="","",L53*D53*55) | O53: =IF(M53="","",M53+N(N53))
A54: 1.3 | B54: 23 | C54: Клапан обратный 16нж10нж Ду 50 Ру 16 | D54: 2 | E54: шт | F54: 50 | G54: 1.6 | H54: 08Х18Н10, 08Х18Н10Т, 12Х18Н9, 12Х18Н9ТЛ | I54: Клапан 16нж10нж является автом | K54: =IF(J54="","",J54*(1-0.1)) | M54: =IF(J54="","",K54*D54) | N54: =IF(L54="","",L54*D54*55) | O54: =IF(M54="","",M54+N(N54))
A55: 1.3 | B55: 24 | C55: Клапан обратный 16нж10нж Ду 32 Ру16 | D55: 5 | E55: шт | F55: 32 | G55: 1.6 | H55: 08Х18Н10, 08Х18Н10Т, 12Х18Н9, 12Х18Н9ТЛ | I55: Клапан 16нж10нж является автом | K55: =IF(J55="","",J55*(1-0.1)) | M55: =IF(J55="","",K55*D55) | N55: =IF(L55="","",L55*D55*55) | O55: =IF(M55="","",M55+N(N55))
A56: 1.3 | B56: 25 | C56: Клапан обратный 16ч42р Ду 100 Ру 2,5 | D56: 3 | E56: шт | F56: 100 | G56: 0.25 | H56: Чугун СЧ 15, СЧ20 | I56: нет | K56: =IF(J56="","",J56*(1-0.1)) | M56: =IF(J56="","",K56*D56) | N56: =IF(L56="","",L56*D56*55) | O56: =IF(M56="","",M56+N(N56))
A57: 1.3 | B57: 26 | C57: Клапан обратный 19нж76нж Ду 100 Ру 16 | D57: 2 | E57: шт | F57: 100 | G57: 1.6 | H57: 12Х18Н9ТЛ | I57: ручное | K57: =IF(J57="","",J57*(1-0.1)) | M57: =IF(J57="","",K57*D57) | N57: =IF(L57="","",L57*D57*55) | O57: =IF(M57="","",M57+N(N57))
A58: 1.3 | B58: 27 | C58: Клапан обратный 19с76нж Ду 80 Ру 16 | D58: 1 | E58: шт | F58: 80 | G58: 1.6 | H58: Сталь 25Л | I58: нет | K58: =IF(J58="","",J58*(1-0.1)) | M58: =IF(J58="","",K58*D58) | N58: =IF(L58="","",L58*D58*55) | O58: =IF(M58="","",M58+N(N58))
A59: 1.3 | B59: 28 | C59: Клапан обратный 19с76нж Ду 100 Ру 16 | D59: 2 | E59: шт | F59: 100 | G59: 1.6 | H59: сталь 25Л, 20, 20Х13 | I59: нет | K59: =IF(J59="","",J59*(1-0.1)) | M59: =IF(J59="","",K59*D59) | N59: =IF(L59="","",L59*D59*55) | O59: =IF(M59="","",M59+N(N59))
A60: 1.3 | B60: 29 | C60: Клапан обратный 19с76нж Ду 50 Ру 16 | D60: 2 | E60: шт | F60: 50 | G60: 1.6 | H60: сталь 25Л, 20, 20Х13 | I60: нет | K60: =IF(J60="","",J60*(1-0.1)) | M60: =IF(J60="","",K60*D60) | N60: =IF(L60="","",L60*D60*55) | O60: =IF(M60="","",M60+N(N60))
A61: 1.3 | B61: 30 | C61: Клапан обратный межфланцевый пружинный тарельчатый NVD-802R Ду 125 Ру 16 | D61: 2 | E61: шт | F61: 125 | G61: 1.6 | H61: серый чугун | K61: =IF(J61="","",J61*(1-0.1)) | M61: =IF(J61="","",K61*D61) | N61: =IF(L61="","",L61*D61*55) | O61: =IF(M61="","",M61+N(N61))
A62: 1.3 | B62: 31 | C62: Клапан обратный межфланцевый пружинный тарельчатый NVD-802R Ду 150 Ру 16 | D62: 10 | E62: шт | F62: 150 | G62: 1.6 | H62: серый чугун | K62: =IF(J62="","",J62*(1-0.1)) | M62: =IF(J62="","",K62*D62) | N62: =IF(L62="","",L62*D62*55) | O62: =IF(M62="","",M62+N(N62))
A63: 1.3 | B63: 32 | C63: Клапан обратный фланцевый пружинный с аксиальным затвором NVD-402R Ду 100 Ру 16 | D63: 2 | E63: шт | F63: 100 | G63: 1.6 | H63: серый чугун | K63: =IF(J63="","",J63*(1-0.1)) | M63: =IF(J63="","",K63*D63) | N63: =IF(L63="","",L63*D63*55) | O63: =IF(M63="","",M63+N(N63))
A64: 1.3 | B64: 33 | C64: Клапан обратный фланцевый пружинный с аксиальным затвором NVD-402R Ду 150 Ру 16 | D64: 5 | E64: шт | F64: 150 | G64: 1.6 | H64: Чугун GG25 с эпоксидным покрытием | I64: - | K64: =IF(J64="","",J64*(1-0.1)) | M64: =IF(J64="","",K64*D64) | N64: =IF(L64="","",L64*D64*55) | O64: =IF(M64="","",M64+N(N64))
A65: 1.3 | B65: 34 | C65: Клапан обратный фланцевый пружинный с аксиальным затвором NVD-402R Ду 200 Ру 16 | D65: 4 | E65: шт | F65: 200 | G65: 1.6 | H65: Чугун GJL250 | K65: =IF(J65="","",J65*(1-0.1)) | M65: =IF(J65="","",K65*D65) | N65: =IF(L65="","",L65*D65*55) | O65: =IF(M65="","",M65+N(N65))
A66: 1.3 | B66: 35 | C66: Обратный клапан пружинный NVD-812R Ду 150 Ру 40 | D66: 1 | E66: шт | F66: 150 | G66: 4 | H66: Нержавеющая сталь | K66: =IF(J66="","",J66*(1-0.1)) | M66: =IF(J66="","",K66*D66) | N66: =IF(L66="","",L66*D66*55) | O66: =IF(M66="","",M66+N(N66))
A67: 1.3 | B67: 36 | C67: Предохранительный клапан ARI-SAFE 12.903 Ду 32/50 Ру 16 | D67: 2 | E67: шт | F67: 32/50 | G67: 1.6 | H67: серый чугун | K67: =IF(J67="","",J67*(1-0.1)) | M67: =IF(J67="","",K67*D67) | N67: =IF(L67="","",L67*D67*55) | O67: =IF(M67="","",M67+N(N67))
A68: 1.3 | B68: 37 | C68: Предохранительный клапан ARI-SAFE 12.903 Ду 25/40 Ру 16 | D68: 2 | E68: шт | F68: 25/40 | G68: 1.6 | H68: серый чугун | K68: =IF(J68="","",J68*(1-0.1)) | M68: =IF(J68="","",K68*D68) | N68: =IF(L68="","",L68*D68*55) | O68: =IF(M68="","",M68+N(N68))
A69: 1.3 | B69: 38 | C69: Предохранительный клапан ARI-SAFE 12.903 Ду 25/40 Ру 16 | D69: 2 | E69: шт | F69: 25/40 | G69: 1.6 | H69: серый чугун | K69: =IF(J69="","",J69*(1-0.1)) | M69: =IF(J69="","",K69*D69) | N69: =IF(L69="","",L69*D69*55) | O69: =IF(M69="","",M69+N(N69))
A70: 1.3 | B70: 39 | C70: Кран для манометра трехходовой Ду 15 Ру 16 | D70: 34 | E70: шт | F70: 15 | G70: 1.6 | H70: латунь ЛЦ40Сд | I70: флажок/рычаг | K70: =IF(J70="","",J70*(1-0.1)) | M70: =IF(J70="","",K70*D70) | N70: =IF(L70="","",L70*D70*55) | O70: =IF(M70="","",M70+N(N70))
A71: 1.3 | B71: 40 | C71: Клапан 22б16п (15б34бк1) запорный вакуумный сильфонный Ду6 Ру16 | D71: 2 | E71: шт | F71: 6 | G71: 1.6 | H71: ЛС59-1Л | I71: Ручной | K71: =IF(J71="","",J71*(1-0.1)) | M71: =IF(J71="","",K71*D71) | N71: =IF(L71="","",L71*D71*55) | O71: =IF(M71="","",M71+N(N71))
A72: 1.3 | B72: 41 | C72: Клапан ВДХ Ду 80 Ру 10 | D72: 2 | E72: шт | F72: 80 | G72: 1.6 | H72: углеродистая сталь | I72: Ручное | K72: =IF(J72="","",J72*(1-0.1)) | M72: =IF(J72="","",K72*D72) | N72: =IF(L72="","",L72*D72*55) | O72: =IF(M72="","",M72+N(N72))
A73: 1.3 | B73: 42 | C73: Клапан диафрагменный химический ВДХ Ду 150 Ру 16 | D73: 1 | E73: шт | F73: 150 | G73: 1.6 | H73: углеродистая сталь | I73: Ручное | K73: =IF(J73="","",J73*(1-0.1)) | M73: =IF(J73="","",K73*D73) | N73: =IF(L73="","",L73*D73*55) | O73: =IF(M73="","",M73+N(N73))
A74: 1.3 | B74: 43 | C74: Клапан диафрагменный химический ВДХ Ду 50, Ру 16 | D74: 1 | E74: шт | F74: 50 | G74: 1.6 | H74: углеродистая сталь | I74: Ручное | K74: =IF(J74="","",J74*(1-0.1)) | M74: =IF(J74="","",K74*D74) | N74: =IF(L74="","",L74*D74*55) | O74: =IF(M74="","",M74+N(N74))
A75: 1.3 | B75: 44 | C75: Клапан диафрагменный химический ВДХ Ду 80 Ру 16 | D75: 3 | E75: шт | F75: 80 | G75: 1.6 | H75: углеродистая сталь | I75: Ручное | K75: =IF(J75="","",J75*(1-0.1)) | M75: =IF(J75="","",K75*D75) | N75: =IF(L75="","",L75*D75*55) | O75: =IF(M75="","",M75+N(N75))
A76: 1.3 | B76: 45 | C76: Клапан запорный 14нж17п Ду 15 Ру 10 цапковый | D76: 2 | E76: шт | F76: 15 | G76: 1 | H76: Сталь марки 12Х18Н9Т | I76: Ручной | K76: =IF(J76="","",J76*(1-0.1)) | M76: =IF(J76="","",K76*D76) | N76: =IF(L76="","",L76*D76*55) | O76: =IF(M76="","",M76+N(N76))
A77: 1.3 | B77: 46 | C77: Клапан запорный 14нж17п Ду 25 Ру 10 цапковый | D77: 2 | E77: шт | F77: 25 | G77: 1 | H77: Сталь марки 12Х18Н9Т | I77: Ручной | K77: =IF(J77="","",J77*(1-0.1)) | M77: =IF(J77="","",K77*D77) | N77: =IF(L77="","",L77*D77*55) | O77: =IF(M77="","",M77+N(N77))
A78: 1.3 | B78: 47 | C78: Клапан запорный 14нж17п Ду 32 Ру 10 цапковый | D78: 1 | E78: шт | F78: 32 | G78: 1 | H78: Сталь марки 12Х18Н9Т | I78: Ручной | K78: =IF(J78="","",J78*(1-0.1)) | M78: =IF(J78="","",K78*D78) | N78: =IF(L78="","",L78*D78*55) | O78: =IF(M78="","",M78+N(N78))
A79: 1.3 | B79: 48 | C79: Клапан запорный 15б1п Ду 15 Ру16 | D79: 45 | E79: шт | F79: 15 | G79: 1.6 | H79: латунь ЛС59-1 ГОСТ 15527-2004 | I79: Ручной | K79: =IF(J79="","",J79*(1-0.1)) | M79: =IF(J79="","",K79*D79) | N79: =IF(L79="","",L79*D79*55) | O79: =IF(M79="","",M79+N(N79))
A80: 1.3 | B80: 49 | C80: Клапан запорный 15б1п Ду 20 Ру16 | D80: 15 | E80: шт | F80: 20 | G80: 1.6 | H80: латунь ЛС59-1 ГОСТ 15527-2004 | I80: Ручной | K80: =IF(J80="","",J80*(1-0.1)) | M80: =IF(J80="","",K80*D80) | N80: =IF(L80="","",L80*D80*55) | O80: =IF(M80="","",M80+N(N80))
A81: 1.3 | B81: 50 | C81: Клапан запорный 15б1п Ду 25 Ру16 | D81: 10 | E81: шт | F81: 25 | G81: 1.6 | H81: латунь ЛС59-1 ГОСТ 15527-2004 | I81: Ручной | K81: =IF(J81="","",J81*(1-0.1)) | M81: =IF(J81="","",K81*D81) | N81: =IF(L81="","",L81*D81*55) | O81: =IF(M81="","",M81+N(N81))
A82: 1.3 | B82: 51 | C82: Клапан запорный 15б1п Ду 32 Ру16 | D82: 10 | E82: шт | F82: 32 | G82: 1.6 | H82: латунь ЛС59-1 ГОСТ 15527-2004 | I82: Ручной | K82: =IF(J82="","",J82*(1-0.1)) | M82: =IF(J82="","",K82*D82) | N82: =IF(L82="","",L82*D82*55) | O82: =IF(M82="","",M82+N(N82))
... A130: 1.3 | B130: 99 | C130: Задвижка 30ч6бр Ду 300 Ру 10 | D130: 4 | E130: шт | F130: 300 | G130: 1 | H130: серый чугун СЧ 18 (СЧ 20) | I130: ручной (маховик) | K130: =IF(J130="","",J130*(1-0.1)) | M130: =IF(J130="","",K130*D130) | N130: =IF(L130="","",L130*D130*55) | O130: =IF(M130="","",M130+N(N130))
A131: 1.3 | B131: 100 | C131: Кран 11б27п(м) Ду 15 Ру 16 3-х ходовой для манометров | D131: 4 | E131: шт | F131: 15 | G131: 1.6 | H131: латунь ЛЦ40Сд | I131: флажок/рычаг | K131: =IF(J131="","",J131*(1-0.1)) | M131: =IF(J131="","",K131*D131) | N131: =IF(L131="","",L131*D131*55) | O131: =IF(M131="","",M131+N(N131))
A132: 1.3 | B132: 101 | C132: Кран шаровой 11б27п1 Ду 15 Ру 16 | D132: 110 | E132: шт | F132: 15 | G132: 1.6 | H132: латунь HPb58-2A | I132: Ручное | K132: =IF(J132="","",J132*(1-0.1)) | M132: =IF(J132="","",K132*D132) | N132: =IF(L132="","",L132*D132*55) | O132: =IF(M132="","",M132+N(N132))
A133: 1.3 | B133: 102 | C133: Кран шаровой 11б27п1 Ду 20 Ру 16 | D133: 57 | E133: шт | F133: 20 | G133: 1.6 | H133: латунь HPb58-2A | I133: Ручное | K133: =IF(J133="","",J133*(1-0.1)) | M133: =IF(J133="","",K133*D133) | N133: =IF(L133="","",L133*D133*55) | O133: =IF(M133="","",M133+N(N133))
A134: 1.3 | B134: 103 | C134: Кран шаровой 11б27п1 Ду 25 Ру 16 | D134: 29 | E134: шт | F134: 25 | G134: 1.6 | H134: латунь HPb58-2A | I134: Ручное | K134: =IF(J134="","",J134*(1-0.1)) | M134: =IF(J134="","",K134*D134) | N134: =IF(L134="","",L134*D134*55) | O134: =IF(M134="","",M134+N(N134))
A135: 1.3 | B135: 104 | C135: Кран шаровой 11б27п1 Ду 32 Ру 16 | D135: 47 | E135: шт | F135: 32 | G135: 1.6 | H135: латунь HPb58-2A | I135: Ручное | K135: =IF(J135="","",J135*(1-0.1)) | M135: =IF(J135="","",K135*D135) | N135: =IF(L135="","",L135*D135*55) | O135: =IF(M135="","",M135+N(N135))
A136: 1.3 | B136: 105 | C136: Кран шаровой 11б27п1 Ду 50 Ру 16 | D136: 24 | E136: шт | F136: 50 | G136: 1.6 | H136: латунь HPb58-2A | I136: Ручное | K136: =IF(J136="","",J136*(1-0.1)) | M136: =IF(J136="","",K136*D136) | N136: =IF(L136="","",L136*D136*55) | O136: =IF(M136="","",M136+N(N136))
A137: 1.3 | B137: 106 | C137: Кран шаровой фланцевый 11с22п Ду 50 Ру 16 | D137: 7 | E137: шт | F137: 50 | G137: 1.6 | H137: сталь 20 | I137: ручной (рукоятка) | K137: =IF(J137="","",J137*(1-0.1)) | M137: =IF(J137="","",K137*D137) | N137: =IF(L137="","",L137*D137*55) | O137: =IF(M137="","",M137+N(N137))
A138: 1.3 | B138: 107 | C138: Кран шаровой фланцевый 11с22п Ду 80 Ру 16 | D138: 8 | E138: шт | F138: 80 | G138: 1.6 | H138: сталь 20 | I138: ручной (рукоятка) | K138: =IF(J138="","",J138*(1-0.1)) | M138: =IF(J138="","",K138*D138) | N138: =IF(L138="","",L138*D138*55) | O138: =IF(M138="","",M138+N(N138))
A139: 1.3 | B139: 108 | C139: Кран шаровой фланцевый 11с22п Ду 100 Ру 16 | D139: 8 | E139: шт | F139: 100 | G139: 1.6 | H139: сталь 20 | I139: ручной (рукоятка) | K139: =IF(J139="","",J139*(1-0.1)) | M139: =IF(J139="","",K139*D139) | N139: =IF(L139="","",L139*D139*55) | O139: =IF(M139="","",M139+N(N139))
A140: 1.3 | B140: 109 | C140: Кран шаровой 11С67П Ду 100 Ру 16 | D140: 2 | E140: шт | F140: 100 | G140: 1.6 | H140: Ст20 | I140: Ручное | K140: =IF(J140="","",J140*(1-0.1)) | M140: =IF(J140="","",K140*D140) | N140: =IF(L140="","",L140*D140*55) | O140: =IF(M140="","",M140+N(N140))
A141: 1.3 | B141: 110 | C141: Кран шаровой 11С67П Ду 150 Ру 16 | D141: 2 | E141: шт | F141: 150 | G141: 1.6 | H141: Ст20 | I141: Ручное | K141: =IF(J141="","",J141*(1-0.1)) | M141: =IF(J141="","",K141*D141) | N141: =IF(L141="","",L141*D141*55) | O141: =IF(M141="","",M141+N(N141))
A142: 1.3 | B142: 111 | C142: Кран шаровой 11С67П Ду 200 Ру 16 | D142: 2 | E142: шт | F142: 200 | G142: 1.6 | H142: Ст20 | I142: Ручное | K142: =IF(J142="","",J142*(1-0.1)) | M142: =IF(J142="","",K142*D142) | N142: =IF(L142="","",L142*D142*55) | O142: =IF(M142="","",M142+N(N142))
A143: 1.3 | B143: 112 | C143: Кран шаровой 11С67П Ду 80 Ру 16 | D143: 2 | E143: шт | F143: 80 | G143: 1.6 | H143: Ст20 | I143: Ручное | K143: =IF(J143="","",J143*(1-0.1)) | M143: =IF(J143="","",K143*D143) | N143: =IF(L143="","",L143*D143*55) | O143: =IF(M143="","",M143+N(N143))
... A193: 1.3 | B193: 162 | C193: Затвор поворотный дисковый Ду 65 Ру 16 ГРАНВЭЛ тип ЗПВС | D193: 2 | E193: шт | F193: 65 | G193: 1.6 | H193: чугун | I193: Ручное | K193: =IF(J193="","",J193*(1-0.1)) | M193: =IF(J193="","",K193*D193) | N193: =IF(L193="","",L193*D193*55) | O193: =IF(M193="","",M193+N(N193))
A194: 1.3 | B194: 163 | C194: Электропривод прямоходный Regada SТ0 490.0-00TQV/00 | D194: 1 | E194: шт | K194: =IF(J194="","",J194*(1-0.1)) | M194: =IF(J194="","",K194*D194) | N194: =IF(L194="","",L194*D194*55) | O194: =IF(M194="","",M194+N(N194))
A195: 1.4 | B195: 1 | C195: Рыбозащитное устройство с потокообразователем | D195: 1 | E195: шт | H195: Сталь 20 | K195: =IF(J195="","",J195*(1-0.1)) | M195: =IF(J195="","",K195*D195) | N195: =IF(L195="","",L195*D195*55) | O195: =IF(M195="","",M195+N(N195))
A196: 1.5 | B196: 1 | C196: Клапан запорный 15кч18п Ду 25 Ру 16 | D196: 11 | E196: шт | F196: 25 | G196: 1.6 | H196: КЧ30 | I196: Ручной | K196: =IF(J196="","",J196*(1-0.1)) | M196: =IF(J196="","",K196*D196) | N196: =IF(L196="","",L196*D196*55) | O196: =IF(M196="","",M196+N(N196))
...

Sheet По таблицам
A1: Таблица | B1: Грузополучатель / статья | C1: Позиций | D1: Единиц | E1: Цен найдено | F1: Себестоимость найденных, ₽
A2: 1.1 | B2: Спец. №1 · Возобновляемая энергетика · ремонт | C2: =COUNTIF(Позиции!A3:A317,"1.1") | D2: =SUMIF(Позиции!A3:A317,"1.1",Позиции!D3:D317) | E2: =COUNTIFS(Позиции!A3:A317,"1.1",Позиции!J3:J317,">0") | F2: =SUMIF(Позиции!A3:A317,"1.1",Позиции!O3:O317)
A3: 1.2 | B3: Спец. №2 · КТЭЦ · ремонт арендованного | C3: =COUNTIF(Позиции!A3:A317,"1.2") | D3: =SUMIF(Позиции!A3:A317,"1.2",Позиции!D3:D317) | E3: =COUNTIFS(Позиции!A3:A317,"1.2",Позиции!J3:J317,">0") | F3: =SUMIF(Позиции!A3:A317,"1.2",Позиции!O3:O317)
A4: 1.3 | B4: Спец. №2 · КТЭЦ · ремонт | C4: =COUNTIF(Позиции!A3:A317,"1.3") | D4: =SUMIF(Позиции!A3:A317,"1.3",Позиции!D3:D317) | E4: =COUNTIFS(Позиции!A3:A317,"1.3",Позиции!J3:J317,">0") | F4: =SUMIF(Позиции!A3:A317,"1.3",Позиции!O3:O317)
A5: 1.4 | B5: Спец. №2 · КТЭЦ · эксплуатация | C5: =COUNTIF(Позиции!A3:A317,"1.4") | D5: =SUMIF(Позиции!A3:A317,"1.4",Позиции!D3:D317) | E5: =COUNTIFS(Позиции!A3:A317,"1.4",Позиции!J3:J317,">0") | F5: =SUMIF(Позиции!A3:A317,"1.4",Позиции!O3:O317)
A6: 1.5 | B6: Спец. №2 · КТЭЦ · ТО | C6: =COUNTIF(Позиции!A3:A317,"1.5") | D6: =SUMIF(Позиции!A3:A317,"1.5",Позиции!D3:D317) | E6: =COUNTIFS(Позиции!A3:A317,"1.5",Позиции!J3:J317,">0") | F6: =SUMIF(Позиции!A3:A317,"1.5",Позиции!O3:O317)
A7: 1.6 | B7: Спец. №3 · Коммунальная энергетика · ремонт | C7: =COUNTIF(Позиции!A3:A317,"1.6") | D7: =SUMIF(Позиции!A3:A317,"1.6",Позиции!D3:D317) | E7: =COUNTIFS(Позиции!A3:A317,"1.6",Позиции!J3:J317,">0") | F7: =SUMIF(Позиции!A3:A317,"1.6",Позиции!O3:O317)
A8: 1.7 | B8: Спец. №3 · Коммунальная энергетика · ТО | C8: =COUNTIF(Позиции!A3:A317,"1.7") | D8: =SUMIF(Позиции!A3:A317,"1.7",Позиции!D3:D317) | E8: =COUNTIFS(Позиции!A3:A317,"1.7",Позиции!J3:J317,">0") | F8: =SUMIF(Позиции!A3:A317,"1.7",Позиции!O3:O317)
A9: 1.8 | B9: Спец. №4 · ЦЭС · ремонт | C9: =COUNTIF(Позиции!A3:A317,"1.8") | D9: =SUMIF(Позиции!A3:A317,"1.8",Позиции!D3:D317) | E9: =COUNTIFS(Позиции!A3:A317,"1.8",Позиции!J3:J317,">0") | F9: =SUMIF(Позиции!A3:A317,"1.8",Позиции!O3:O317)
